Metadata-Version: 2.1
Name: orbitx
Version: 0.0
Summary: Propagate satellite orbits to identify matchups.
Home-page: https://gitlab.npl.co.uk/eco/tools/orbitx
Author: Sajedeh Behnia
Author-email: sajedeh.behnia@npl.co.uk
License: None
Classifier: Development Status :: 2 - Pre-Alpha
Classifier: Programming Language :: Python
Classifier: Programming Language :: Python :: 3.6
Classifier: Programming Language :: Python :: 3.7
Classifier: Programming Language :: Python :: 3.8
Provides-Extra: dev
